HMKamene/__init__.py
HMKamene/arp.py
HMKamene/sniff.py
HMKamene-1.0.4.dist-info/LICENSE.txt
HMKamene-1.0.4.dist-info/METADATA
HMKamene-1.0.4.dist-info/WHEEL
HMKamene-1.0.4.dist-info/top_level.txt
HMKamene-1.0.4.dist-info/RECORD
