Metadata-Version: 2.1
Name: HMKamene
Version: 1.0.4
Summary: A package contains a generic functions and classes
Home-page: https://github.com/pypa/sampleproject
Author: HM
License: UNKNOWN
Platform: UNKNOWN
Classifier: Programming Language :: Python :: 3
Classifier: License :: OSI Approved :: MIT License
Classifier: Operating System :: OS Independent
Requires-Python: >=3
Requires-Dist: HMGeneric
